lego_certbot.py
lego_certbot-1.0.0.dist-info/entry_points.txt
lego_certbot-1.0.0.dist-info/LICENSE
lego_certbot-1.0.0.dist-info/METADATA
lego_certbot-1.0.0.dist-info/WHEEL
lego_certbot-1.0.0.dist-info/RECORD
