Metadata-Version: 2.1
Name: lego-certbot
Version: 1.0.0
Summary: Lego DNS-01 exec provider script for Certbot authenticator plugins
Home-page: https://github.com/Callum027/lego-certbot
License: MIT
Keywords: certbot,lego,letsencrypt,dns-01
Author: Callum Dickinson
Author-email: callum.dickinson.nz@gmail.com
Requires-Python: >=3.8.1,<4.0.0
Classifier: Development Status :: 5 - Production/Stable
Classifier: Environment :: Console
Classifier: Intended Audience :: System Administrators
Classifier: License :: OSI Approved :: MIT License
Classifier: Natural Language :: English
Classifier: Operating System :: OS Independent
Classifier: Programming Language :: Python :: 3
Classifier: Programming Language :: Python :: 3.9
Classifier: Programming Language :: Python :: 3.10
Classifier: Programming Language :: Python :: 3.11
Classifier: Programming Language :: Python :: 3.8
Classifier: Topic :: System :: Systems Administration
Requires-Dist: certbot
Requires-Dist: importlib-metadata (>=4.6.0)
Project-URL: Documentation, https://github.com/Callum027/lego-certbot/blob/main/README.md
Project-URL: Repository, https://github.com/Callum027/lego-certbot
